imfdatapy/__inti__.py
imfdatapy/imf.py
imfdatapy/imf_log.py
imfdatapy-1.0.0.dist-info/LICENSE
imfdatapy-1.0.0.dist-info/WHEEL
imfdatapy-1.0.0.dist-info/METADATA
imfdatapy-1.0.0.dist-info/RECORD
