Metadata-Version: 2.1
Name: imfdatapy
Version: 1.0.0
Summary: A package for data discovery and extraction from the IMF!
License: Apache v2.0
Author: Irina Klein, Sou-Cheng T. Choi
Requires-Python: >=3.7.15,<3.11
Classifier: License :: Other/Proprietary License
Classifier: Programming Language :: Python :: 3
Classifier: Programming Language :: Python :: 3.8
Classifier: Programming Language :: Python :: 3.9
Classifier: Programming Language :: Python :: 3.10
Requires-Dist: numpy (>=1.21.6)
Requires-Dist: pandas (>=1.3.5)
Requires-Dist: requests (>=2.23.0)
